LICENSE.txt
MANIFEST.in
README.rst
VERSION
setup.cfg
setup.py
mlmorph_spellchecker/__init__.py
mlmorph_spellchecker/__main__.py
mlmorph_spellchecker/spellchecker.py
mlmorph_spellchecker/suggestion.py
mlmorph_spellchecker/utils.py
mlmorph_spellchecker.egg-info/PKG-INFO
mlmorph_spellchecker.egg-info/SOURCES.txt
mlmorph_spellchecker.egg-info/dependency_links.txt
mlmorph_spellchecker.egg-info/entry_points.txt
mlmorph_spellchecker.egg-info/not-zip-safe
mlmorph_spellchecker.egg-info/requires.txt
mlmorph_spellchecker.egg-info/top_level.txt
mlmorph_spellchecker/resources/common_mistakes.csv
mlmorph_spellchecker/strategies/__init__.py
mlmorph_spellchecker/strategies/chillu_normalization.py
mlmorph_spellchecker/strategies/chillu_to_virama_form.py
mlmorph_spellchecker/strategies/consonant_virama_to_chillu.py
mlmorph_spellchecker/strategies/geminate_consonants.py
mlmorph_spellchecker/strategies/insert_y_before_kkuka.py
mlmorph_spellchecker/strategies/mpa_correction.py
mlmorph_spellchecker/strategies/nta_correction.py
mlmorph_spellchecker/strategies/phonetic_similarity.py
mlmorph_spellchecker/strategies/suggestion_strategy.py
mlmorph_spellchecker/strategies/virama_insertion.py
mlmorph_spellchecker/strategies/visual_similarity.py
mlmorph_spellchecker/strategies/vowel_elongation.py
mlmorph_spellchecker/strategies/vowel_shortening.py