Metadata-Version: 2.1
Name: mlmorph-spellchecker
Version: 1.1.1
Summary: Malayalam morphology analyser based spellchecker
Home-page: https://gitlab.com/smc/mlmorph-spellchecker
Author: Santhosh Thottingal
Author-email: santhosh.thottingal@gmail.com
License: MIT
Keywords: Malayalam morphology FST analyser generator spellchecker
Platform: UNKNOWN
Classifier: Programming Language :: Python :: 3
Classifier: Programming Language :: Python :: 3.5
Classifier: Programming Language :: Python :: 3.6
Classifier: Programming Language :: Python :: 3.7
Classifier: Programming Language :: Python :: 3.8
Classifier: License :: OSI Approved :: MIT License
Classifier: Topic :: Software Development :: Libraries
Classifier: Intended Audience :: Developers
